keypad/__init__.py
keypad/src/__init__.py
keypad/src/keypad.py
micro_keypad-0.0.3.dist-info/LICENSE
micro_keypad-0.0.3.dist-info/METADATA
micro_keypad-0.0.3.dist-info/WHEEL
micro_keypad-0.0.3.dist-info/top_level.txt
micro_keypad-0.0.3.dist-info/RECORD
