Metadata-Version: 2.1
Name: micro-keypad
Version: 0.0.3
Summary: The Keypad library is designed to simplify keypad interfacing in Micropython-based hardware projects.
Home-page: https://github.com/thecircuitproject/micropython-keypad
Author: José Carlos Borrayo Tojín
Author-email: thecircuitproject1@gmail.com
License: MIT
Requires-Python: >=3.4
License-File: LICENSE
Provides-Extra: dev
Requires-Dist: pytest ; extra == 'dev'
Requires-Dist: twine >=5.1.1 ; extra == 'dev'
